exmc/__init__.py
exmc/__main__.py
exmc/convert.py
exmc-0.0.3.dist-info/entry_points.txt
exmc-0.0.3.dist-info/LICENSE
exmc-0.0.3.dist-info/WHEEL
exmc-0.0.3.dist-info/METADATA
exmc-0.0.3.dist-info/RECORD
