Metadata-Version: 2.1
Name: exmc
Version: 0.0.3
Summary: Excel Markdown Converter
Home-page: https://github.com/idlewith/exmc
License: MIT
Author: idlewith
Author-email: newellzhou@163.com
Requires-Python: >=3.7,<4.0
Classifier: Development Status :: 5 - Production/Stable
Classifier: License :: OSI Approved :: MIT License
Classifier: Programming Language :: Python :: 3
Classifier: Programming Language :: Python :: 3.7
Classifier: Programming Language :: Python :: 3.8
Classifier: Programming Language :: Python :: 3.9
Classifier: Programming Language :: Python :: 3.10
Requires-Dist: clipboard (>=0.0.4,<0.0.5)
Project-URL: Changelog, https://github.com/idlewith/exmc/releases
Project-URL: Documentation, https://exmc.readthedocs.io
Project-URL: Repository, https://github.com/idlewith/exmc
